<?xml version="1.0" encoding="UTF-8"?>
<!DOCTYPE tiles-definitions PUBLIC "-//Apache Software Foundation//DTD Tiles Configuration 3.0//EN"
        "http://tiles.apache.org/dtds/tiles-config_3_0.dtd">
<tiles-definitions>
    <definition name="mainTemplate" template="/WEB-INF/pages/layouts/mainLayout.jsp">
        <put-attribute name="header" value="" cascade="true" />
        <put-attribute name="footer" value="" cascade="true" />
        <put-attribute name="menu" value="" cascade="true"  />
        <put-attribute name="body" value="" cascade="true" />
        <put-attribute name="resources" value="" cascade="true" />
    </definition>
    <definition name="homeView" extends="mainTemplate">
        <put-attribute name="header" value="/WEB-INF/pages/tiles/header.jsp" cascade="true" />
        <put-attribute name="footer" value="/WEB-INF/pages/tiles/footer.jsp" cascade="true" />
        <put-attribute name="menu" value="/WEB-INF/pages/tiles/menu.jsp" cascade="true"  />
        <put-attribute name="body" value="/WEB-INF/pages/home.jsp" cascade="true" />
        <put-attribute name="resources" value="" cascade="true" />
    </definition>

    <!--introduction-->
    <definition name="introductionTopicsView" extends="mainTemplate">
        <put-attribute name="header" value="/WEB-INF/pages/tiles/header.jsp" cascade="true" />
        <put-attribute name="footer" value="/WEB-INF/pages/tiles/footer.jsp" cascade="true" />
        <put-attribute name="menu" value="/WEB-INF/pages/tiles/menu.jsp" cascade="true"  />
        <put-attribute name="body" value="/WEB-INF/pages/introduction/introductionTopics.jsp" cascade="true" />
        <put-attribute name="resources" value="" cascade="true" />
    </definition>
    <definition name="introductionInReactJSView" extends="mainTemplate">
        <put-attribute name="header" value="/WEB-INF/pages/tiles/header.jsp" cascade="true" />
        <put-attribute name="footer" value="/WEB-INF/pages/tiles/footer.jsp" cascade="true" />
        <put-attribute name="menu" value="/WEB-INF/pages/introduction/menu.jsp" cascade="true"  />
        <put-attribute name="body" value="/WEB-INF/pages/introduction/introductionInReactJS.jsp" cascade="true" />
        <put-attribute name="resources" value="" cascade="true" />
    </definition>
    <definition name="installationView" extends="mainTemplate">
        <put-attribute name="header" value="/WEB-INF/pages/tiles/header.jsp" cascade="true" />
        <put-attribute name="footer" value="/WEB-INF/pages/tiles/footer.jsp" cascade="true" />
        <put-attribute name="menu" value="/WEB-INF/pages/introduction/menu.jsp" cascade="true"  />
        <put-attribute name="body" value="/WEB-INF/pages/introduction/instalation.jsp" cascade="true" />
        <put-attribute name="resources" value="" cascade="true" />
    </definition>
    <definition name="devtoolsView" extends="mainTemplate">
        <put-attribute name="header" value="/WEB-INF/pages/tiles/header.jsp" cascade="true" />
        <put-attribute name="footer" value="/WEB-INF/pages/tiles/footer.jsp" cascade="true" />
        <put-attribute name="menu" value="/WEB-INF/pages/introduction/menu.jsp" cascade="true"  />
        <put-attribute name="body" value="/WEB-INF/pages/introduction/devtools.jsp" cascade="true" />
        <put-attribute name="resources" value="" cascade="true" />
    </definition>

    <!--basics-->
    <definition name="basicsTopicsView" extends="mainTemplate">
        <put-attribute name="header" value="/WEB-INF/pages/tiles/header.jsp" cascade="true" />
        <put-attribute name="footer" value="/WEB-INF/pages/tiles/footer.jsp" cascade="true" />
        <put-attribute name="menu" value="/WEB-INF/pages/tiles/menu.jsp" cascade="true"  />
        <put-attribute name="body" value="/WEB-INF/pages/basics/basicsTopics.jsp" cascade="true" />
        <put-attribute name="resources" value="" cascade="true" />
    </definition>
    <definition name="noteToJavaScriptView" extends="mainTemplate">
        <put-attribute name="header" value="/WEB-INF/pages/tiles/header.jsp" cascade="true" />
        <put-attribute name="footer" value="/WEB-INF/pages/tiles/footer.jsp" cascade="true" />
        <put-attribute name="menu" value="/WEB-INF/pages/basics/menu.jsp" cascade="true"  />
        <put-attribute name="body" value="/WEB-INF/pages/basics/noteToJavaScript.jsp" cascade="true" />
        <put-attribute name="resources" value="" cascade="true" />
    </definition>
    <definition name="helloWorldExampleView" extends="mainTemplate">
        <put-attribute name="header" value="/WEB-INF/pages/tiles/header.jsp" cascade="true" />
        <put-attribute name="footer" value="/WEB-INF/pages/tiles/footer.jsp" cascade="true" />
        <put-attribute name="menu" value="/WEB-INF/pages/basics/menu.jsp" cascade="true"  />
        <put-attribute name="body" value="/WEB-INF/pages/basics/helloWorldExample.jsp" cascade="true" />
        <put-attribute name="resources" value="" cascade="true" />
    </definition>
    <definition name="introductionToJsxView" extends="mainTemplate">
        <put-attribute name="header" value="/WEB-INF/pages/tiles/header.jsp" cascade="true" />
        <put-attribute name="footer" value="/WEB-INF/pages/tiles/footer.jsp" cascade="true" />
        <put-attribute name="menu" value="/WEB-INF/pages/basics/menu.jsp" cascade="true"  />
        <put-attribute name="body" value="/WEB-INF/pages/basics/introductionToJsx.jsp" cascade="true" />
        <put-attribute name="resources" value="" cascade="true" />
    </definition>
    <definition name="renderingElementsView" extends="mainTemplate">
        <put-attribute name="header" value="/WEB-INF/pages/tiles/header.jsp" cascade="true"/>
        <put-attribute name="footer" value="/WEB-INF/pages/tiles/footer.jsp" cascade="true"/>
        <put-attribute name="menu" value="/WEB-INF/pages/basics/menu.jsp" cascade="true"/>
        <put-attribute name="body" value="/WEB-INF/pages/basics/renderingElements.jsp" cascade="true"/>
        <put-attribute name="resources" value="" cascade="true"/>
    </definition>
    <definition name="componentsAndPropsView" extends="mainTemplate">
        <put-attribute name="header" value="/WEB-INF/pages/tiles/header.jsp" cascade="true"/>
        <put-attribute name="footer" value="/WEB-INF/pages/tiles/footer.jsp" cascade="true"/>
        <put-attribute name="menu" value="/WEB-INF/pages/basics/menu.jsp" cascade="true"/>
        <put-attribute name="body" value="/WEB-INF/pages/basics/componentsAndProps.jsp" cascade="true"/>
        <put-attribute name="resources" value="" cascade="true"/>
    </definition>
    <definition name="stateAndLifecycleView" extends="mainTemplate">
        <put-attribute name="header" value="/WEB-INF/pages/tiles/header.jsp" cascade="true"/>
        <put-attribute name="footer" value="/WEB-INF/pages/tiles/footer.jsp" cascade="true"/>
        <put-attribute name="menu" value="/WEB-INF/pages/basics/menu.jsp" cascade="true"/>
        <put-attribute name="body" value="/WEB-INF/pages/basics/stateAndLifecycle.jsp" cascade="true"/>
        <put-attribute name="resources" value="" cascade="true"/>
    </definition>
    <definition name="handlingEventsView" extends="mainTemplate">
        <put-attribute name="header" value="/WEB-INF/pages/tiles/header.jsp" cascade="true"/>
        <put-attribute name="footer" value="/WEB-INF/pages/tiles/footer.jsp" cascade="true"/>
        <put-attribute name="menu" value="/WEB-INF/pages/basics/menu.jsp" cascade="true"/>
        <put-attribute name="body" value="/WEB-INF/pages/basics/handlingEvents.jsp" cascade="true"/>
        <put-attribute name="resources" value="" cascade="true"/>
    </definition>
    <definition name="conditionalRenderingView" extends="mainTemplate">
        <put-attribute name="header" value="/WEB-INF/pages/tiles/header.jsp" cascade="true"/>
        <put-attribute name="footer" value="/WEB-INF/pages/tiles/footer.jsp" cascade="true"/>
        <put-attribute name="menu" value="/WEB-INF/pages/basics/menu.jsp" cascade="true"/>
        <put-attribute name="body" value="/WEB-INF/pages/basics/conditionalRendering.jsp" cascade="true"/>
        <put-attribute name="resources" value="" cascade="true"/>
    </definition>
    <definition name="listsAndKeysView" extends="mainTemplate">
        <put-attribute name="header" value="/WEB-INF/pages/tiles/header.jsp" cascade="true"/>
        <put-attribute name="footer" value="/WEB-INF/pages/tiles/footer.jsp" cascade="true"/>
        <put-attribute name="menu" value="/WEB-INF/pages/basics/menu.jsp" cascade="true"/>
        <put-attribute name="body" value="/WEB-INF/pages/basics/listsAndKeys.jsp" cascade="true"/>
        <put-attribute name="resources" value="" cascade="true"/>
    </definition>
</tiles-definitions>